index_next/__init__.py
index_next-0.2.dist-info/LICENSE
index_next-0.2.dist-info/METADATA
index_next-0.2.dist-info/WHEEL
index_next-0.2.dist-info/top_level.txt
index_next-0.2.dist-info/RECORD
