Metadata-Version: 2.1
Name: index_next
Version: 0.2
Summary: usage: from index_next import get_next_index
Author: Artie Dins
License: Apache-2.0
Project-URL: Homepage, https://github.com/artiedins/index_next
License-File: LICENSE
